{
 "14794": {
  "len": 4320,
  "tableBlock": "t;/p&gt;<p><strong>Šėrimo instrukcija:</strong></p>\n<style>.b2b-black, .b2b-black * { color:#000 !important; }</style><div class=\"b2b-black\"><table style=\"width:100%;\" cellspacing=\"0\">\n<tr><td style=\"border-bottom: 2px solid #d3d3d3;padding: 7px;\"><b>Šuns svoris</b></td><td style=\"border-bottom: 2px solid #d3d3d3;padding: 7px;\"><b>Kiekis per parą</b></td></tr>\n<tr><td style=\"border-bottom: 2px solid #d3d3d3;padding: 7px;\">25 kg</td><td style=\"border-bottom: 2px solid #d3d3d3;padding: 7px;\">295–340 g</td></tr>\n<tr><td style=\"border-bottom: 2px solid #d3d3d3;padding: 7px;\">30 kg</td><td style=\"border-bottom: 2px solid #d3d3d3;padding: 7px;\">335–390 g</td></tr>\n<tr><td style=\"border-bottom: 2px solid #d3d3d3;padding: 7px;\">35 kg</td><td style=\"border-bottom: 2px solid #d3d3d3;padding: 7px;\">375–435 g</td></tr>\n<tr><td style=\"border-bottom: 2px solid #d3d3d3;padding: 7px;\">40 kg</td><td style=\"border-bottom: 2px solid #d3d3d3;padding: 7px;\">415–485 g</td></tr>\n<tr><td style=\"border-bottom: 2px solid #d3d3d3;padding: 7px;\">50 kg</td><td style=\"border-bottom: 2px solid #d3d3d3;padding: 7px;\">495–570 g</td></tr>\n<tr><td style=\"border-bottom: 2px solid #d3d3d3;padding: 7px;\">70 kg</td><td style=\"border-bottom: 2px solid #d3d3d3;padding: 7px;\">635–735 g</td></tr>\n<tr><td style=\"border-bottom: 2px solid #d3d3d3;padding: 7px;\">90 kg</td><td style=\"border-bottom: 2px solid #d3d3d3;padding: 7px;\">765–885 g</td></tr>\n</table>"
 },
 "33452": {
  "len": 4026,
  "tableBlock": "t;/p&gt;<p><strong>Šėrimo instrukcija:</strong></p>\n<style>.b2b-black, .b2b-black * { color:#000 !important; }</style><div class=\"b2b-black\"><table style=\"width:100%;\" cellspacing=\"0\">\n<tr><td style=\"border-bottom: 2px solid #d3d3d3;padding: 7px;\"><b>Šuns svoris</b></td><td style=\"border-bottom: 2px solid #d3d3d3;padding: 7px;\"><b>Kiekis per parą</b></td></tr>\n<tr><td style=\"border-bottom: 2px solid #d3d3d3;padding: 7px;\">2 kg</td><td style=\"border-bottom: 2px solid #d3d3d3;padding: 7px;\">45–50 g</td></tr>\n<tr><td style=\"border-bottom: 2px solid #d3d3d3;padding: 7px;\">5 kg</td><td style=\"border-bottom: 2px solid #d3d3d3;padding: 7px;\">80–90 g</td></tr>\n<tr><td style=\"border-bottom: 2px solid #d3d3d3;padding: 7px;\">10 kg</td><td style=\"border-bottom: 2px solid #d3d3d3;padding: 7px;\">125–140 g</td></tr>\n<tr><td style=\"border-bottom: 2px solid #d3d3d3;padding: 7px;\">20 kg</td><td style=\"border-bottom: 2px solid #d3d3d3;padding: 7px;\">200–220 g</td></tr>\n<tr><td style=\"border-bottom: 2px solid #d3d3d3;padding: 7px;\">30 kg</td><td style=\"border-bottom: 2px solid #d3d3d3;padding: 7px;\">265–290 g</td></tr>\n<tr><td style=\"border-bottom: 2px solid #d3d3d3;padding: 7px;\">40 kg</td><td style=\"border-bottom: 2px solid #d3d3d3;padding: 7px;\">320–355 g</td></tr>\n<tr><td style=\"border-bottom: 2px solid #d3d3d3;padding: 7px;\">50 kg</td><td style=\"border-bottom: 2px solid #d3d3d3;padding: 7px;\">370–410 g</td></tr>\n<tr><td style=\"border-bottom: 2px solid #d3d3d3;padding: 7px;\">60 kg</td><td style=\"border-bottom: 2px solid #d3d3d3;padding: 7px;\">420–465 g</td></tr>\n<tr><td style=\"border-bottom: 2px solid #d3d3d3;padding: 7px;\">70 kg</td><td style=\"border-bottom: 2px solid #d3d3d3;padding: 7px;\">465–515 g</td></tr>\n</table>"
 }
}