{"a":{"199":{"inserted":7,"backup":"/home/gyvunai2/domains/avesa.lt/public_html/dev/wp-content/uploads/ps_private/backup_feeding_199_20260721_164112.json","repo":"OK","support":"calculator_supported","rows":["2.00kg:45.00-55.00","3.00kg:65.00-75.00","4.00kg:75.00-85.00","5.00kg:85.00-95.00","6.00kg:95.00-115.00","8.00kg:115.00-135.00","10.00kg:135.00-155.00"]},"243":{"inserted":9,"backup":"/home/gyvunai2/domains/avesa.lt/public_html/dev/wp-content/uploads/ps_private/backup_feeding_243_20260721_164112.json","repo":"OK","support":"calculator_supported","rows":["11.00kg:145.00-165.00","15.00kg:185.00-205.00","20.00kg:210.00-235.00","25.00kg:270.00-300.00","30.00kg:320.00-350.00","40.00kg:430.00-470.00","50.00kg:470.00-505.00","60.00kg:490.00-525.00","70.00kg:540.00-580.00"]}}}