{"cleaned_583":true,"sid":586,"test":"{\"fee_code\":{\"functions.php\":\"==============================================================\\n\\/\\/ Mazo krepselio mokestis + pranesimai\\n\\/\\/ ===============================================================\\nadd_action( 'woocommerce_cart_calculate_fees', function() {\\n    if ( is_admin() && ! defined( 'DOING_AJAX' ) ) return;\\n    $threshold     = 9.00;\\n    $fee           = 1.00;\\n    $subtotal_incl = WC()->cart->get_subtotal() + WC()->cart->get_subtotal_tax();\\n    if ( $subtotal_incl <= $threshold ) {\\n        WC()->cart->add_fee( 'Ma\\u017eo krep\\u0161elio mokestis', $fee, true );\\n    }\\n} );\\n\\n\\/\\/ Prane\\u0161imas krep\\u0161elio suvestin\\u0117je (de\\u0161in\\u0117je) po mokes\\u010dio eilute\\nadd_action('woocommerce_cart_totals_after_order_total', function() {\\n    $thr\"},\"cheap_product\":\"Susid\\u0117k kramtal\\u0173 rinkin\\u012f \\u00b7 Ma\\u017eam \\u0161uniui \\u00b7 3 vnt (pasl\\u0117ptas)\",\"cheap_price\":3.9,\"test_1x\":{\"subtotal\":\"3.22\",\"fees\":[\"Ma\\u017eo krep\\u0161elio mokestis=1\"]},\"test_3x\":{\"subtotal\":\"9.67\",\"fees\":[]},\"test_5x\":{\"subtotal\":\"16.12\",\"fees\":[]}}"}