{"create":{"id":1207,"code_error":null},"d":{"readonly":true,"p3_parity_live_rest":{"2":{"MATCH":true,"status":"ok","tier":"B1","portion":{"min":50,"max":60}},"5":{"MATCH":true,"status":"ok","tier":"B1","portion":{"min":90,"max":100}},"7":{"MATCH":true,"status":"ok","tier":"B2","portion":{"min":110,"max":130}},"10":{"MATCH":true,"status":"ok","tier":"B1","portion":{"min":140,"max":160}},"9.5":{"MATCH":true,"status":"ok","tier":"B2","portion":{"min":135,"max":155}}},"p3_PASS":true,"p4":{"flat_status":"OK","flat_portion":[110,124],"nested_raw_status":"D","nested_normalized_status":"OK","nested_normalized_portion":[110,124],"PASS":true}}}