{
 "robots_head": "User-Agent: *\r\nDisallow: /global\r\nDisallow: /temp/\r\nDisallow: /upload/\r\nDisallow: /xsl/\r\nDisallow: /*/api/\r\nDisallow: /*/*/api/\r\nDisallow: /*/cart\r\nDisallow: /*/checkout\r\nDisallow: /*/checkout/confirmation\r\nDisallow: /*/*/register\r\nDisallow: /*/view-all-products\r\nDisallow: /*/view-all-articles\r\nDisa",
 "maps": [
  "https://www.royalcanin.com/ae/sitemap.xml",
  "https://www.royalcanin.com/ar/sitemap.xml",
  "https://www.royalcanin.com/at/sitemap.xml",
  "https://www.royalcanin.com/au/sitemap.xml",
  "https://www.royalcanin.com/be/sitemap.xml",
  "https://www.royalcanin.com/be/nl-be/sitemap.xml",
  "https://www.royalcanin.com/bg/sitemap.xml",
  "https://www.royalcanin.com/br/sitemap.xml"
 ],
 "lt_urls": 0,
 "prod_n": 0,
 "sample": [],
 "hit_n": 0,
 "hits": []
}