{"sid":597,"err":"","result":"{\"presets\":[{\"id\":34433,\"title\":\"Tualet\\u0173 filtras\",\"slug\":\"tualetu-filtras\",\"filters\":[]},{\"id\":34118,\"title\":\"Akvariumo zuvu filtras\",\"slug\":\"akvariumo-zuvu-filtras\",\"filters\":[]},{\"id\":34117,\"title\":\"Paukscio rusis filtras\",\"slug\":\"paukscio-rusis-filtras\",\"filters\":[]},{\"id\":34115,\"title\":\"Grauziko rusis filtras\",\"slug\":\"grauziko-rusis-filtras\",\"filters\":[]},{\"id\":34114,\"title\":\"Tevines kategorijos filtras\",\"slug\":\"tevine-filtras\",\"filters\":[]},{\"id\":34108,\"title\":\"\\u0160uk\\u0173 filtras\",\"slug\":\"suku-filtras\",\"filters\":[]},{\"id\":34107,\"title\":\"\\u0160amp\\u016bn\\u0173 filtras\",\"slug\":\"sampunu-filtras\",\"filters\":[]},{\"id\":34105,\"title\":\"Draskykli\\u0173 filtras\",\"slug\":\"draskykliu-filtras\",\"filters\":[]},{\"id\":34104,\"title\":\"Aprangos filtras\",\"slug\":\"apranga-filtras\",\"filters\":[]},{\"id\":34103,\"title\":\"Kraik\\u0173 filtras\",\"slug\":\"kraiku-filtras\",\"filters\":[]},{\"id\":34102,\"title\":\"\\u017daisl\\u0173 filtras\",\"slug\":\"zaislu-filtras\",\"filters\":[]},{\"id\":34083,\"title\":\"Guoli\\u0173\\/transporto filtras\",\"slug\":\"guoliu-transporto-filtras\",\"filters\":[]},{\"id\":34082,\"title\":\"Duben\\u0117li\\u0173 filtras\",\"slug\":\"dubeneliu-filtras\",\"filters\":[]},{\"id\":34081,\"title\":\"Antkakli\\u0173 filtras\",\"slug\":\"antkakliu-filtras\",\"filters\":[]},{\"id\":34080,\"title\":\"Vitamin\\u0173 filtras\",\"slug\":\"vitaminu-filtras\",\"filters\":[]},{\"id\":34070,\"title\":\"Skan\\u0117st\\u0173 filtras\",\"slug\":\"skanestu-filtras\",\"filters\":[]},{\"id\":34063,\"title\":\"Maisto filtras\",\"slug\":\"maisto-filtras\",\"filters\":[]},{\"id\":6644,\"title\":\"Pagrindinis\",\"slug\":\"default-preset\",\"filters\":[]}],\"lookup_exists\":true,\"lookup_rows\":12943,\"lookup_be_grudu\":1753,\"lookup_speciali\":385,\"lookup_taxonomies\":[\"pa_amzius\",\"pa_baltymu_saltinis\",\"pa_be_grudu\",\"pa_dydis\",\"pa_forma\",\"pa_grauziko_rusis\",\"pa_gyvuno_rusis\",\"pa_ilgis\",\"pa_kiekis_pakuoteje\",\"pa_kraiko_tipas\",\"pa_kvapas\",\"pa_medziaga\",\"pa_monoprotein\",\"pa_pakuotes_dydis\",\"pa_pasaro_forma\",\"pa_paskirtis\",\"pa_paukscio_rusis\",\"pa_pavadelio_ilgis\",\"pa_spalva\",\"pa_speciali_mityba\",\"pa_tipas\",\"pa_veisle\",\"pa_zaislo_tipas\",\"pa_zuvies_rusis\"],\"term_counts\":{\"pa_be_grudu\":\"ERROR: netinkama taksonomija.\",\"pa_speciali_mityba\":\"ERROR: netinkama taksonomija.\",\"pa_monoprotein\":[\"Ne(64)\",\"Taip(434)\"]}}"}