[{"d":["page_view","mobile"],"m":[89064,23180]},{"d":["user_engagement","mobile"],"m":[87744,20713]},{"d":["view_item_list","mobile"],"m":[40181,11235]},{"d":["page_view","desktop"],"m":[26927,4366]},{"d":["view_item","mobile"],"m":[26056,13480]},{"d":["user_engagement","desktop"],"m":[25614,4533]},{"d":["session_start","mobile"],"m":[23215,23320]},{"d":["first_visit","mobile"],"m":[16951,16947]},{"d":["view_item_list","desktop"],"m":[12843,2785]},{"d":["scroll","mobile"],"m":[12116,5812]},{"d":["view_item","desktop"],"m":[6142,2440]},{"d":["view_cart","mobile"],"m":[5514,1953]},{"d":["add_to_cart","mobile"],"m":[5002,2108]},{"d":["session_start","desktop"],"m":[4676,4730]},{"d":["scroll","desktop"],"m":[4093,1648]},{"d":["form_start","mobile"],"m":[3005,1575]},{"d":["form_submit","mobile"],"m":[2770,1506]},{"d":["first_visit","desktop"],"m":[2514,2512]},{"d":["begin_checkout","mobile"],"m":[1971,1525]},{"d":["add_to_cart","desktop"],"m":[1741,629]},{"d":["view_cart","desktop"],"m":[1631,573]},{"d":["page_view","tablet"],"m":[1474,261]},{"d":["add_payment_info","mobile"],"m":[1424,1145]},{"d":["add_shipping_info","mobile"],"m":[1419,1144]},{"d":["user_engagement","tablet"],"m":[1332,223]},{"d":["form_start","desktop"],"m":[1294,590]},{"d":["form_submit","desktop"],"m":[1213,564]},{"d":["purchase","mobile"],"m":[1094,1086]},{"d":["view_item_list","tablet"],"m":[770,176]},{"d":["begin_checkout","desktop"],"m":[683,543]},{"d":["add_shipping_info","desktop"],"m":[463,364]},{"d":["add_payment_info","desktop"],"m":[462,363]},{"d":["purchase","desktop"],"m":[452,450]},{"d":["view_item","tablet"],"m":[291,116]},{"d":["scroll","tablet"],"m":[262,90]},{"d":["session_start","tablet"],"m":[259,259]},{"d":["first_visit","tablet"],"m":[150,150]},{"d":["view_cart","tablet"],"m":[128,31]},{"d":["add_to_cart","tablet"],"m":[114,34]},{"d":["Phone_click","mobile"],"m":[106,96]},{"d":["Email_click","mobile"],"m":[72,67]},{"d":["form_start","tablet"],"m":[61,24]},{"d":["form_submit","tablet"],"m":[59,24]},{"d":["add_shipping_info","tablet"],"m":[33,21]},{"d":["add_payment_info","tablet"],"m":[32,20]},{"d":["begin_checkout","tablet"],"m":[31,23]},{"d":["Email_click","desktop"],"m":[17,6]},{"d":["purchase","tablet"],"m":[17,17]},{"d":["click","desktop"],"m":[8,7]},{"d":["Phone_copy","desktop"],"m":[7,7]},{"d":["Email_copy","desktop"],"m":[5,5]},{"d":["Phone_click","desktop"],"m":[5,5]},{"d":["click","mobile"],"m":[5,5]},{"d":["Phone_click","tablet"],"m":[2,2]}]